[
{
    "employeeId" : "829384751",
    "firstName" : "Anthony",
    "lastName" : "Rizzo",
    "opCo" : "Aerotek",
    "email" : "arizzo@cubs.com",
    "cellPhone" : "3125550001"
},
{
    "employeeId" : "111194803",
    "firstName" : "Kris",
    "lastName" : "Bryant",
    "opCo" : "TEKsystems",
    "email" : "kb@cubs.com",
    "cellPhone" : "3125550002"
},
{
    "employeeId" : "669922773",
    "firstName" : "Kyle",
    "lastName" : "Schwarber",
    "opCo" : "ACS",
    "email" : "kb@cubs.com",
    "cellPhone" : "3125550003"
},
{
    "employeeId" : "200998554",
    "firstName" : "Jake",
    "lastName" : "Arrietta",
    "opCo" : "MLA",
    "email" : "jarrietta@cubs.com",
    "cellPhone" : "3125550004"
},
{
    "employeeId" : "300922821",
    "firstName" : "Javier",
    "lastName" : "Baez",
    "opCo" : "AGS",
    "email" : "jbaez@cubs.com",
    "cellPhone" : "3125550005"
}
]
